LICENSE
MANIFEST.in
README.md
setup.py
NlpToolkit_PropBank_Cy.egg-info/PKG-INFO
NlpToolkit_PropBank_Cy.egg-info/SOURCES.txt
NlpToolkit_PropBank_Cy.egg-info/dependency_links.txt
NlpToolkit_PropBank_Cy.egg-info/top_level.txt
PropBank/Argument.c
PropBank/Argument.pxd
PropBank/Argument.pyx
PropBank/ArgumentList.c
PropBank/ArgumentList.pxd
PropBank/ArgumentList.pyx
PropBank/ArgumentType.py
PropBank/Frameset.c
PropBank/Frameset.pxd
PropBank/Frameset.pyx
PropBank/FramesetArgument.c
PropBank/FramesetArgument.pxd
PropBank/FramesetArgument.pyx
PropBank/FramesetList.c
PropBank/FramesetList.pxd
PropBank/FramesetList.pyx
PropBank/Predicate.c
PropBank/Predicate.pxd
PropBank/Predicate.pyx
PropBank/PredicateList.c
PropBank/PredicateList.pyx
PropBank/Role.c
PropBank/Role.pxd
PropBank/Role.pyx
PropBank/RoleSet.c
PropBank/RoleSet.pxd
PropBank/RoleSet.pyx
PropBank/__init__.py
PropBank/data/__init__.py
PropBank/data/english-propbank.xml
PropBank/data/turkish-propbank.xml
nlptoolkit_propBank_cy.egg-info/PKG-INFO
nlptoolkit_propBank_cy.egg-info/SOURCES.txt
nlptoolkit_propBank_cy.egg-info/dependency_links.txt
nlptoolkit_propBank_cy.egg-info/top_level.txt