Metadata-Version: 2.1
Name: nlptoolkit-propBank-cy
Version: 1.0.17
Summary: Turkish PropBank
Home-page: https://github.com/StarlangSoftware/TurkishPropbank-Cy
Author: olcaytaner
Author-email: olcay.yildiz@ozyegin.edu.tr
License: UNKNOWN
Platform: UNKNOWN
